{
  "warmups": [
    {
      "type": "warmup",
      "title": "Arm Circles",
      "steps": [
        "Stand with feet shoulder-width apart.",
        "Extend arms out to the sides.",
        "Make small forward circles for 15 seconds.",
        "Switch to backward circles for 15 seconds."
      ],
      "video_url": "https://www.youtube.com/watch?v=U5LtNciLz1k",
      "new": false,
      "age_group": "8-9",
      "skill_level": "beginner"
    },
    {
      "type": "warmup",
      "title": "High Knees",
      "steps": [
        "Stand tall with feet hip-width apart.",
        "Run in place while lifting knees to waist height.",
        "Keep core engaged and move arms naturally."
      ],
      "video_url": "https://www.youtube.com/watch?v=8opcQdC-V-U",
      "new": false,
      "age_group": "8-9",
      "skill_level": "beginner"
    },
    {
      "type": "warmup",
      "title": "World's Greatest Stretch",
      "tags": ["injury-prevention"],
      "steps": [
        "Start in a lunge position with right foot forward.",
        "Place left hand on ground, rotate right arm toward ceiling.",
        "Hold for a few seconds, return, then switch sides.",
        "Do 5 reps per side."
      ],
      "video_url": "https://www.youtube.com/watch?v=F4S1Fyh4HAg",
      "new": true,
      "age_group": "12-13",
      "skill_level": "advanced"
    },
    {
      "type": "warmup",
      "title": "Inchworm Stretch",
      "tags": ["injury-prevention", "core-activation"],
      "steps": [
        "Stand tall, reach down and touch toes.",
        "Walk hands forward to push-up position.",
        "Hold for 2 seconds, then walk feet toward hands.",
        "Repeat for 30 seconds."
      ],
      "video_url": "https://www.youtube.com/watch?v=lYlNnLazCwA",
      "new": true,
      "age_group": "10-11",
      "skill_level": "intermediate"
    },
    {
      "type": "warmup",
      "title": "Glute Bridge",
      "tags": ["injury-prevention", "hip-activation"],
      "steps": [
        "Lie on your back with knees bent, feet flat.",
        "Lift hips up while squeezing glutes.",
        "Hold for 2 seconds, lower down slowly.",
        "Repeat for 10 reps."
      ],
      "video_url": "https://www.youtube.com/watch?v=m2Zx-57cSok",
      "new": true,
      "age_group": "12-13",
      "skill_level": "advanced"
    }
  ],
  "conditioning": [
    {
      "type": "conditioning",
      "title": "Shuttle Runs",
      "steps": [
        "Set two cones 10 yards apart.",
        "Sprint from one cone to the other and back.",
        "Repeat for 30 seconds with rest intervals."
      ],
      "video_url": "https://www.youtube.com/watch?v=j2e1YjzXz-A",
      "new": false,
      "age_group": "10-11",
      "skill_level": "intermediate"
    },
    {
      "type": "conditioning",
      "title": "Lateral Skater Hops",
      "steps": [
        "Start in a half-squat position.",
        "Jump laterally to the right, landing on the right foot.",
        "Push off and jump to the left.",
        "Repeat for 30 seconds."
      ],
      "video_url": "https://www.youtube.com/watch?v=FUX6Pz8vV0s",
      "new": true,
      "age_group": "10-11",
      "skill_level": "intermediate"
    },
    {
      "type": "conditioning",
      "title": "Jumping Jacks",
      "steps": [
        "Start with feet together and arms at sides.",
        "Jump while spreading feet and raising arms overhead.",
        "Return to starting position and repeat for 30 seconds."
      ],
      "video_url": "https://www.youtube.com/watch?v=c4DAnQ6DtF8",
      "new": false,
      "age_group": "8-9",
      "skill_level": "beginner"
    },
    {
      "type": "conditioning",
      "title": "Bear Crawls",
      "steps": [
        "Start on hands and feet (not knees), hips up.",
        "Crawl forward using opposite hand and foot.",
        "Go 10 yards, then rest.",
        "Repeat 2-3 times."
      ],
      "video_url": "https://www.youtube.com/watch?v=gMaB-fG4u4g",
      "new": false,
      "age_group": "12-13",
      "skill_level": "advanced"
    }
  ]
}

